{
  "Foundation": {
    "Foundation": {
      "general": {
        "neutral": {
          "50": {
            "$type": "color",
            "$value": "#f7f9f"
          },
          "100": {
            "$type": "color",
            "$value": "#f2f4f8"
          },
          "200": {
            "$type": "color",
            "$value": "#e5e9ef"
          },
          "300": {
            "$type": "color",
            "$value": "#dadfe5"
          },
          "400": {
            "$type": "color",
            "$value": "#c6cdd5"
          },
          "500": {
            "$type": "color",
            "$value": "#a8b0bd"
          },
          "600": {
            "$type": "color",
            "$value": "#66768a"
          },
          "700": {
            "$type": "color",
            "$value": "#52647a"
          },
          "800": {
            "$type": "color",
            "$value": "#44586d"
          },
          "900": {
            "$type": "color",
            "$value": "#2e3d4b"
          },
          "950": {
            "$type": "color",
            "$value": "#1f2124"
          },
          "00": {
            "$type": "color",
            "$value": "#fff"
          }
        },
        "brand": {
          "50": {
            "$type": "color",
            "$value": "#fff1df"
          },
          "100": {
            "$type": "color",
            "$value": "#ffdcb4"
          },
          "200": {
            "$type": "color",
            "$value": "#ffc995"
          },
          "300": {
            "$type": "color",
            "$value": "#fea764"
          },
          "400": {
            "$type": "color",
            "$value": "#fd7f37"
          },
          "500": {
            "$type": "color",
            "$value": "#fc671a"
          },
          "600": {
            "$type": "color",
            "$value": "#c2330a"
          },
          "700": {
            "$type": "color",
            "$value": "#992e10"
          },
          "800": {
            "$type": "color",
            "$value": "#79270f"
          },
          "900": {
            "$type": "color",
            "$value": "#5c1d0c"
          },
          "950": {
            "$type": "color",
            "$value": "#3f1308"
          }
        },
        "info": {
          "50": {
            "$type": "color",
            "$value": "#ebf6ff"
          },
          "100": {
            "$type": "color",
            "$value": "#cce6ff"
          },
          "200": {
            "$type": "color",
            "$value": "#add8ff"
          },
          "300": {
            "$type": "color",
            "$value": "#81c1ff"
          },
          "400": {
            "$type": "color",
            "$value": "#57a6ff"
          },
          "500": {
            "$type": "color",
            "$value": "#4297ff"
          },
          "600": {
            "$type": "color",
            "$value": "#125fe3"
          },
          "700": {
            "$type": "color",
            "$value": "#1549c1"
          },
          "800": {
            "$type": "color",
            "$value": "#0d39a0"
          },
          "900": {
            "$type": "color",
            "$value": "#0b238e"
          },
          "950": {
            "$type": "color",
            "$value": "#061567"
          }
        },
        "success": {
          "50": {
            "$type": "color",
            "$value": "#e2f9e9"
          },
          "100": {
            "$type": "color",
            "$value": "#beedcc"
          },
          "200": {
            "$type": "color",
            "$value": "#98e3b3"
          },
          "300": {
            "$type": "color",
            "$value": "#5bd18d"
          },
          "400": {
            "$type": "color",
            "$value": "#24ba6a"
          },
          "500": {
            "$type": "color",
            "$value": "#1bab60"
          },
          "600": {
            "$type": "color",
            "$value": "#0e7744"
          },
          "700": {
            "$type": "color",
            "$value": "#0e6039"
          },
          "800": {
            "$type": "color",
            "$value": "#0c4c2f"
          },
          "900": {
            "$type": "color",
            "$value": "#093a24"
          },
          "950": {
            "$type": "color",
            "$value": "#052718"
          }
        },
        "warning": {
          "50": {
            "$type": "color",
            "$value": "#fff2d5"
          },
          "100": {
            "$type": "color",
            "$value": "#ffde96"
          },
          "200": {
            "$type": "color",
            "$value": "#ffca66"
          },
          "300": {
            "$type": "color",
            "$value": "#ffa926"
          },
          "400": {
            "$type": "color",
            "$value": "#f98307"
          },
          "500": {
            "$type": "color",
            "$value": "#ef7204"
          },
          "600": {
            "$type": "color",
            "$value": "#b83f06"
          },
          "700": {
            "$type": "color",
            "$value": "#97300c"
          },
          "800": {
            "$type": "color",
            "$value": "#79270d"
          },
          "900": {
            "$type": "color",
            "$value": "#5e1c05"
          },
          "950": {
            "$type": "color",
            "$value": "#421102"
          }
        },
        "critical": {
          "50": {
            "$type": "color",
            "$value": "#fef0ef"
          },
          "100": {
            "$type": "color",
            "$value": "#ffdad6"
          },
          "200": {
            "$type": "color",
            "$value": "#ffc5c0"
          },
          "300": {
            "$type": "color",
            "$value": "#ffa399"
          },
          "400": {
            "$type": "color",
            "$value": "#fd7c70"
          },
          "500": {
            "$type": "color",
            "$value": "#f96657"
          },
          "600": {
            "$type": "color",
            "$value": "#cd1c07"
          },
          "700": {
            "$type": "color",
            "$value": "#a12113"
          },
          "800": {
            "$type": "color",
            "$value": "#7d2119"
          },
          "900": {
            "$type": "color",
            "$value": "#611711"
          },
          "950": {
            "$type": "color",
            "$value": "#450c08"
          }
        },
        "intelligence": {
          "50": {
            "$type": "color",
            "$value": "#f5f2ff"
          },
          "100": {
            "$type": "color",
            "$value": "#e5deff"
          },
          "200": {
            "$type": "color",
            "$value": "#d7cbff"
          },
          "300": {
            "$type": "color",
            "$value": "#c5afff"
          },
          "400": {
            "$type": "color",
            "$value": "#b28fff"
          },
          "500": {
            "$type": "color",
            "$value": "#a87eff"
          },
          "600": {
            "$type": "color",
            "$value": "#7f31fd"
          },
          "700": {
            "$type": "color",
            "$value": "#6a0be1"
          },
          "800": {
            "$type": "color",
            "$value": "#5816a9"
          },
          "900": {
            "$type": "color",
            "$value": "#441280"
          },
          "950": {
            "$type": "color",
            "$value": "#2d0c5a"
          }
        },
        "alpha": {
          "50": {
            "$type": "color",
            "$value": "rgba(0, 0, 0, 6%)"
          },
          "100": {
            "$type": "color",
            "$value": "rgba(0, 0, 0, 8%)"
          },
          "200": {
            "$type": "color",
            "$value": "rgba(0, 0, 0, 16%)"
          },
          "300": {
            "$type": "color",
            "$value": "rgba(0, 0, 0, 28%)"
          },
          "400": {
            "$type": "color",
            "$value": "rgba(0, 0, 0, 36%)"
          },
          "500": {
            "$type": "color",
            "$value": "rgba(0, 0, 0, 60%)"
          },
          "00": {
            "$type": "color",
            "$value": "transparent"
          }
        }
      },
      "data": {
        "categorical": {
          "10": {
            "$type": "color",
            "$value": "#00518b"
          },
          "11": {
            "$type": "color",
            "$value": "#a37530"
          },
          "12": {
            "$type": "color",
            "$value": "#fdd886"
          },
          "13": {
            "$type": "color",
            "$value": "#7f67bf"
          },
          "14": {
            "$type": "color",
            "$value": "#58be1d"
          },
          "15": {
            "$type": "color",
            "$value": "#d7f8ae"
          },
          "16": {
            "$type": "color",
            "$value": "#a1b4c5"
          },
          "17": {
            "$type": "color",
            "$value": "#5cb9f4"
          },
          "18": {
            "$type": "color",
            "$value": "#e13038"
          },
          "19": {
            "$type": "color",
            "$value": "#1f3d57"
          },
          "20": {
            "$type": "color",
            "$value": "#2c91d4"
          },
          "21": {
            "$type": "color",
            "$value": "#ac5a03"
          },
          "01": {
            "$type": "color",
            "$value": "#157bc1"
          },
          "02": {
            "$type": "color",
            "$value": "#f9ad24"
          },
          "03": {
            "$type": "color",
            "$value": "#f74f57"
          },
          "04": {
            "$type": "color",
            "$value": "#c3b3e8"
          },
          "05": {
            "$type": "color",
            "$value": "#94e1e3"
          },
          "06": {
            "$type": "color",
            "$value": "#9a0165"
          },
          "07": {
            "$type": "color",
            "$value": "#ff9da2"
          },
          "08": {
            "$type": "color",
            "$value": "#4c657b"
          },
          "09": {
            "$type": "color",
            "$value": "#a8e07e"
          }
        }
      }
    },
    "$metadata": {
      "tokenSetOrder": {
        "0": {
          "$type": "other",
          "$value": "Foundation"
        }
      }
    }
  },
  "$themes": [
    {
      "id": "f396bad429cd316544081eba22e6b8eeb569a300",
      "name": "Light mode",
      "$figmaStyleReferences": {},
      "selectedTokenSets": {},
      "group": "Prism"
    }
  ],
  "$metadata": {
    "tokenSetOrder": [
      "Foundation"
    ]
  }
}